[{"id":"tk1b-1","name":"Electrike","set":{"id":"tk1b","name":"EX Trainer Kit Latios","series":"EX","printedTotal":10,"total":10,"legalities":{"unlimited":"Legal"},"releaseDate":"2004/06/01","updatedAt":"2022/01/13 20:44:00","images":{"symbol":"https://images.pokemontcg.io/tk1b/symbol.png","logo":"https://images.pokemontcg.io/tk1b/logo.png"}},"number":"1","images":{"small":"https://images.pokemontcg.io/tk1b/1.png","large":"https://images.pokemontcg.io/tk1b/1_hires.png"}},{"id":"tk1b-2","name":"Latios","set":{"id":"tk1b","name":"EX Trainer Kit Latios","series":"EX","printedTotal":10,"total":10,"legalities":{"unlimited":"Legal"},"releaseDate":"2004/06/01","updatedAt":"2022/01/13 20:44:00","images":{"symbol":"https://images.pokemontcg.io/tk1b/symbol.png","logo":"https://images.pokemontcg.io/tk1b/logo.png"}},"number":"2","images":{"small":"https://images.pokemontcg.io/tk1b/2.png","large":"https://images.pokemontcg.io/tk1b/2_hires.png"}},{"id":"tk1b-3","name":"Linoone","set":{"id":"tk1b","name":"EX Trainer Kit Latios","series":"EX","printedTotal":10,"total":10,"legalities":{"unlimited":"Legal"},"releaseDate":"2004/06/01","updatedAt":"2022/01/13 20:44:00","images":{"symbol":"https://images.pokemontcg.io/tk1b/symbol.png","logo":"https://images.pokemontcg.io/tk1b/logo.png"}},"number":"3","images":{"small":"https://images.pokemontcg.io/tk1b/3.png","large":"https://images.pokemontcg.io/tk1b/3_hires.png"}},{"id":"tk1b-4","name":"Magnemite","set":{"id":"tk1b","name":"EX Trainer Kit Latios","series":"EX","printedTotal":10,"total":10,"legalities":{"unlimited":"Legal"},"releaseDate":"2004/06/01","updatedAt":"2022/01/13 20:44:00","images":{"symbol":"https://images.pokemontcg.io/tk1b/symbol.png","logo":"https://images.pokemontcg.io/tk1b/logo.png"}},"number":"4","images":{"small":"https://images.pokemontcg.io/tk1b/4.png","large":"https://images.pokemontcg.io/tk1b/4_hires.png"}},{"id":"tk1b-5","name":"Magneton","set":{"id":"tk1b","name":"EX Trainer Kit Latios","series":"EX","printedTotal":10,"total":10,"legalities":{"unlimited":"Legal"},"releaseDate":"2004/06/01","updatedAt":"2022/01/13 20:44:00","images":{"symbol":"https://images.pokemontcg.io/tk1b/symbol.png","logo":"https://images.pokemontcg.io/tk1b/logo.png"}},"number":"5","images":{"small":"https://images.pokemontcg.io/tk1b/5.png","large":"https://images.pokemontcg.io/tk1b/5_hires.png"}},{"id":"tk1b-6","name":"Pikachu","set":{"id":"tk1b","name":"EX Trainer Kit Latios","series":"EX","printedTotal":10,"total":10,"legalities":{"unlimited":"Legal"},"releaseDate":"2004/06/01","updatedAt":"2022/01/13 20:44:00","images":{"symbol":"https://images.pokemontcg.io/tk1b/symbol.png","logo":"https://images.pokemontcg.io/tk1b/logo.png"}},"number":"6","images":{"small":"https://images.pokemontcg.io/tk1b/6.png","large":"https://images.pokemontcg.io/tk1b/6_hires.png"}},{"id":"tk1b-7","name":"Zigzagoon","set":{"id":"tk1b","name":"EX Trainer Kit Latios","series":"EX","printedTotal":10,"total":10,"legalities":{"unlimited":"Legal"},"releaseDate":"2004/06/01","updatedAt":"2022/01/13 20:44:00","images":{"symbol":"https://images.pokemontcg.io/tk1b/symbol.png","logo":"https://images.pokemontcg.io/tk1b/logo.png"}},"number":"7","images":{"small":"https://images.pokemontcg.io/tk1b/7.png","large":"https://images.pokemontcg.io/tk1b/7_hires.png"}},{"id":"tk1b-8","name":"Potion","set":{"id":"tk1b","name":"EX Trainer Kit Latios","series":"EX","printedTotal":10,"total":10,"legalities":{"unlimited":"Legal"},"releaseDate":"2004/06/01","updatedAt":"2022/01/13 20:44:00","images":{"symbol":"https://images.pokemontcg.io/tk1b/symbol.png","logo":"https://images.pokemontcg.io/tk1b/logo.png"}},"number":"8","images":{"small":"https://images.pokemontcg.io/tk1b/8.png","large":"https://images.pokemontcg.io/tk1b/8_hires.png"}},{"id":"tk1b-9","name":"Energy Search","set":{"id":"tk1b","name":"EX Trainer Kit Latios","series":"EX","printedTotal":10,"total":10,"legalities":{"unlimited":"Legal"},"releaseDate":"2004/06/01","updatedAt":"2022/01/13 20:44:00","images":{"symbol":"https://images.pokemontcg.io/tk1b/symbol.png","logo":"https://images.pokemontcg.io/tk1b/logo.png"}},"number":"9","images":{"small":"https://images.pokemontcg.io/tk1b/9.png","large":"https://images.pokemontcg.io/tk1b/9_hires.png"}},{"id":"tk1b-10","name":"Lightning Energy","set":{"id":"tk1b","name":"EX Trainer Kit Latios","series":"EX","printedTotal":10,"total":10,"legalities":{"unlimited":"Legal"},"releaseDate":"2004/06/01","updatedAt":"2022/01/13 20:44:00","images":{"symbol":"https://images.pokemontcg.io/tk1b/symbol.png","logo":"https://images.pokemontcg.io/tk1b/logo.png"}},"number":"10","images":{"small":"https://images.pokemontcg.io/tk1b/10.png","large":"https://images.pokemontcg.io/tk1b/10_hires.png"}}]